{
  "name": "Lizadro Dark Theme",
  "colors": {
    "activityBar.activeBorder": "#ce5412",
    "activityBar.background": "#141414",
    "activityBar.border": "#00000060",
    "activityBar.foreground": "#eeffff",
    "activityBarBadge.background": "#ce5412",
    "activityBarBadge.foreground": "#ffffff",
    "badge.background": "#00000030",
    "badge.foreground": "#4a4a4a",
    "breadcrumb.activeSelectionForeground": "#80cbc4",
    "breadcrumb.background": "#080808",
    "breadcrumb.focusForeground": "#eeffff",
    "breadcrumb.foreground": "#848484",
    "breadcrumbPicker.background": "#1a1a1a",
    "button.background": "#61616150",
    "button.foreground": "#ffffff",
    "button.hoverBackground": "#6087cf",
    "debugConsole.errorForeground": "#f07178",
    "debugConsole.infoForeground": "#89ddff",
    "debugConsole.warningForeground": "#ffcb6b",
    "debugToolBar.background": "#212121",
    "diffEditor.insertedTextBackground": "#89ddff20",
    "diffEditor.removedTextBackground": "#ff9cac20",
    "dropdown.background": "#151515",
    "dropdown.border": "#6087cf",
    "editor.background": "#0a0b0f",
    "editor.findMatchBackground": "#000000",
    "editor.findMatchBorder": "#80cbc4",
    "editor.findMatchHighlightBackground": "#00000050",
    "editor.findMatchHighlightBorder": "#ffffff50",
    "editor.findRangeHighlightBackground": "#ffcb6b30",
    "editor.foreground": "#eeffff",
    "editor.lineHighlightBackground": "#00000050",
    "editor.lineHighlightBorder": "#00000000",
    "editor.rangeHighlightBackground": "#ffffff0d",
    "editor.selectionBackground": "#3f5a5e",
    "editor.selectionHighlightBackground": "#ffcc0020",
    "editor.selectionHighlightBorder": "#ffffff",
    "editor.wordHighlightBackground": "#ff9cac30",
    "editor.wordHighlightStrongBackground": "#c3e88d30",
    "editorBracketMatch.background": "#212121",
    "editorBracketMatch.border": "#ffd700",
    "editorCursor.foreground": "#ffff00",
    "editorError.foreground": "#f0717870",
    "editorGroup.border": "#00000030",
    "editorGroup.dropBackground": "#f0717880",
    "editorGroup.focusedEmptyBorder": "#f07178",
    "editorGroupHeader.tabsBackground": "#080808",
    "editorGutter.addedBackground": "#c3e88d60",
    "editorGutter.background": "#0a0b0f",
    "editorGutter.deletedBackground": "#f0717860",
    "editorGutter.modifiedBackground": "#82aaff60",
    "editorHoverWidget.background": "#212121",
    "editorHoverWidget.border": "#ffffff10",
    "editorIndentGuide.activeBackground": "#424242",
    "editorIndentGuide.background": "#42424270",
    "editorInfo.foreground": "#82aaff70",
    "editorInlayHint.background": "#2c313a",
    "editorInlayHint.foreground": "#636e83",
    "editorLineNumber.activeForeground": "#d6801d",
    "editorLineNumber.foreground": "#7b7b7b",
    "editorLink.activeForeground": "#eeffff",
    "editorMarkerNavigation.background": "#eeffff05",
    "editorOverviewRuler.border": "#212121",
    "editorOverviewRuler.errorForeground": "#f0717840",
    "editorOverviewRuler.findMatchForeground": "#80cbc4",
    "editorOverviewRuler.infoForeground": "#82aaff40",
    "editorOverviewRuler.warningForeground": "#ffcb6b40",
    "editorRuler.foreground": "#424242",
    "editorSuggestWidget.background": "#212121",
    "editorSuggestWidget.border": "#ffffff10",
    "editorSuggestWidget.foreground": "#eeffff",
    "editorSuggestWidget.highlightForeground": "#80cbc4",
    "editorSuggestWidget.selectedBackground": "#00000050",
    "editorWarning.foreground": "#ffcb6b70",
    "editorWhitespace.foreground": "#eeffff40",
    "editorWidget.background": "#1a1a1a",
    "editorWidget.border": "#80cbc4",
    "editorWidget.resizeBorder": "#80cbc4",
    "extensionButton.prominentBackground": "#2ba143",
    "extensionButton.prominentHoverBackground": "#37af4e",
    "focusBorder": "#1a1a1a",
    "input.background": "#1b1d23",
    "input.border": "#181a1f",
    "list.activeSelectionBackground": "#2c313a",
    "list.activeSelectionForeground": "#d7dae0",
    "list.focusBackground": "#2c313a",
    "list.highlightForeground": "#d7dae0",
    "list.hoverBackground": "#2c313a66",
    "list.inactiveSelectionBackground": "#2c313a",
    "list.inactiveSelectionForeground": "#d7dae0",
    "notebook.cellEditorBackground": "#2c313a",
    "peekView.border": "#528bff",
    "peekViewEditor.background": "#1b1d23",
    "peekViewResult.background": "#21252b",
    "peekViewResult.selectionBackground": "#2c313a",
    "peekViewTitle.background": "#1b1d23",
    "pickerGroup.border": "#528bff",
    "scrollbarSlider.activeBackground": "#747d9180",
    "scrollbarSlider.background": "#4e566680",
    "scrollbarSlider.hoverBackground": "#5a637580",
    "sideBar.background": "#0a0b0f",
    "sideBarSectionHeader.background": "#333842",
    "sideBar.border": "#2c313a",
    "statusBar.background": "#141414",
    "statusBar.debuggingForeground": "#ffffff",
    "statusBar.foreground": "#9da5b4",
    "statusBar.noFolderBackground": "#21252b",
    "statusBarItem.hoverBackground": "#2c313a",
    "tab.activeBackground": "#22323b",
    "tab.activeForeground": "#d7dae0",
    "tab.border": "#22323b",
    "tab.inactiveBackground": "#080808",
    "terminalCursor.foreground": "#ffff00",
    "titleBar.activeBackground": "#141414",
    "titleBar.activeForeground": "#9da5b4",
    "titleBar.inactiveBackground": "#141414",
    "titleBar.inactiveForeground": "#9da5b4",
    "widget.shadow": "#ffffff00"
  },
  "tokenColors": [
    {
      "scope": [
        "comment",
        "comment keyword",
        "comment markup.underline.link",
        "comment string",
        "comment punctuation.definition",
        "comment punctuation",
        "comment text"
      ],
      "settings": {
        "foreground": "#696D77",
        "fontStyle": "italic"
      }
    },
    {
      "scope": "comment storage.type",
      "settings": {
        "foreground": "#696D77"
      }
    },
    {
      "scope": "comment entity.name.type",
      "settings": {
        "foreground": "#B2B9BD"
      }
    },
    {
      "scope": ["comment variable", "comment variable.other"],
      "settings": {
        "foreground": "#B2B9BD"
      }
    },
    {
      "scope": "comment keyword.codetag.notation",
      "settings": {
        "foreground": "#C39AC9"
      }
    },
    {
      "scope": "comment.git-status.header.remote",
      "settings": {
        "foreground": "#FF657A"
      }
    },
    {
      "scope": "comment.git-status.header.local",
      "settings": {
        "foreground": "#9CD1BB"
      }
    },
    {
      "scope": "comment.other.git-status.head",
      "settings": {
        "foreground": "#EAF2F1"
      }
    },
    {
      "scope": [
        "string.quoted.docstring",
        "string.quoted.docstring punctuation.definition"
      ],
      "settings": {
        "foreground": "#696D77"
      }
    },
    {
      "scope": "constant",
      "settings": {
        "foreground": "#C39AC9"
      }
    },
    {
      "scope": "constant.other",
      "settings": {
        "foreground": "#EAF2F1"
      }
    },
    {
      "scope": "constant.other.caps",
      "settings": {
        "foreground": "#C39AC9"
      }
    },
    {
      "scope": "constant.other.placeholder.c",
      "settings": {
        "foreground": "#FF9B5E"
      }
    },
    {
      "scope": "constant.other.property",
      "settings": {
        "foreground": "#C39AC9"
      }
    },
    {
      "scope": "constant.other.citation.latex",
      "settings": {
        "foreground": "#C39AC9"
      }
    },
    {
      "scope": "constant.other.color",
      "settings": {
        "foreground": "#a6a6a6"
      }
    },
    {
      "scope": "constant.other.character-class.escape",
      "settings": {
        "foreground": "#C39AC9"
      }
    },
    {
      "scope": "constant.other.key",
      "settings": {
        "foreground": "#C39AC9"
      }
    },
    {
      "scope": "constant.other.symbol",
      "settings": {
        "foreground": "#FF9B5E"
      }
    },
    {
      "scope": "constant.other.elm",
      "settings": {
        "foreground": "#9CD1BB"
      }
    },
    {
      "scope": "constant.numeric",
      "settings": {
        "foreground": "#ffffff"
      }
    },
    {
      "scope": "constant.language",
      "settings": {
        "foreground": "#C39AC9"
      }
    },
    {
      "scope": "constant.character.escape",
      "settings": {
        "foreground": "#C39AC9"
      }
    },
    {
      "scope": "constant.numeric.line-number.find-in-files",
      "settings": {
        "foreground": "#535763"
      }
    },
    {
      "scope": "constant.numeric.line-number.match.find-in-files",
      "settings": {
        "foreground": "#FFD76D"
      }
    },
    {
      "scope": "entity.name.section",
      "settings": {
        "foreground": "#FFD76D"
      }
    },
    {
      "scope": [
        "entity.name.function",
        "entity.name.function.templated",
        "entity.name.function.member.static"
      ],
      "settings": {
        "foreground": "#BAD761"
      }
    },
    {
      "scope": [
        "entity.name.type.class.templated",
        "entity.name.type.class.generic",
        "entity.name.type.namespace"
      ],
      "settings": {
        "foreground": "#9CD1BB"
      }
    },
    {
      "scope": "entity.name.label",
      "settings": {
        "foreground": "#C39AC9"
      }
    },
    {
      "scope": "entity.name.function.preprocessor",
      "settings": {
        "foreground": "#9CD1BB"
      }
    },
    {
      "scope": "entity.name",
      "settings": {
        "foreground": "#BAD761"
      }
    },
    {
      "scope": "entity.name.class",
      "settings": {
        "foreground": "#9CD1BB"
      }
    },
    {
      "scope": "entity.name.constant",
      "settings": {
        "foreground": "#C39AC9"
      }
    },
    {
      "scope": "entity.name.namespace",
      "settings": {
        "foreground": "#EAF2F1"
      }
    },
    {
      "scope": "entity.other.inherited-class",
      "settings": {
        "foreground": "#9CD1BB",
        "fontStyle": "italic"
      }
    },
    {
      "scope": "entity.name.function",
      "settings": {
        "foreground": "#BAD761"
      }
    },
    {
      "scope": ["entity.name.tag"],
      "settings": {
        "foreground": "#d9ed92"
      }
    },
    {
      "scope": [
        "entity.name.tag.js.jsx support.class.component.js.jsx",
        "entity.name.tag support.class.component",
        "source.vue support.class.component"
      ],
      "settings": {
        "foreground": "#1ff87d"
      }
    },
    {
      "scope": "entity.name.function.operator",
      "settings": {
        "foreground": "#FF657A"
      }
    },
    {
      "scope": "entity.name.tag.css",
      "settings": {
        "foreground": "#ff84d0"
      }
    },
    {
      "scope": [
        "meta.brackets entity.name.function.operator",
        "punctuation.separator entity.name.function.operator"
      ],
      "settings": {
        "foreground": "#8a9488"
      }
    },
    {
      "scope": [
        "entity.name.type",
        "entity.name.type.class.reference",
        "entity.name.type.class.value"
      ],
      "settings": {
        "foreground": "#9CD1BB"
      }
    },
    {
      "scope": "entity.other.attribute-name",
      "settings": {
        "foreground": "#9CD1BB",
        "fontStyle": "italic"
      }
    },
    {
      "scope": [
        "entity.other.attribute-name.class.css",
        "entity.other.attribute-name.parent-selector-suffix.css",
        "entity.other.attribute-name.parent-selector-suffix.css punctuation.definition.entity.css",
        "entity.other.attribute-name.css",
        "entity.other.animation-name.css"
      ],
      "settings": {
        "foreground": "#9de7ff"
      }
    },
    {
      "scope": "entity.other.attribute-name.id.css",
      "settings": {
        "foreground": "#FF9B5E"
      }
    },
    {
      "scope": [
        "entity.other.attribute-name.pseudo-class.css",
        "entity.other.pseudo-class.css",
        "entity.other.pseudo-element.css"
      ],
      "settings": {
        "foreground": "#b87bc1",
        "fontStyle": "italic"
      }
    },
    {
      "scope": ["entity.name.function", "support.function"],
      "settings": {
        "foreground": "#bfff00"
      }
    },
    {
      "scope": "entity.other.git-status.hex",
      "settings": {
        "foreground": "#C39AC9"
      }
    },
    {
      "scope": "entity.other.jinja2.delimiter",
      "settings": {
        "foreground": "#888D94"
      }
    },
    {
      "scope": "entity.name.operator.custom-literal",
      "settings": {
        "foreground": "#EAF2F1"
      }
    },
    {
      "scope": "entity.name.operator.custom-literal.string",
      "settings": {
        "foreground": "#FFD76D"
      }
    },
    {
      "scope": "entity.name.operator.custom-literal.number",
      "settings": {
        "foreground": "#C39AC9"
      }
    },
    {
      "scope": "entity.name.type.rust",
      "settings": {
        "foreground": "#9CD1BB"
      }
    },
    {
      "scope": "entity.name.lifetime.rust",
      "settings": {
        "foreground": "#FF657A"
      }
    },
    {
      "scope": "invalid",
      "settings": {
        "foreground": "#FF657A",
        "fontStyle": "italic underline"
      }
    },
    {
      "scope": "invalid.deprecated",
      "settings": {
        "foreground": "#FF9B5E",
        "fontStyle": "italic underline"
      }
    },
    {
      "scope": "keyword",
      "settings": {
        "foreground": "#ffa200"
      }
    },
    {
      "scope": "keyword.control",
      "settings": {
        "foreground": "#0fcdd3"
      }
    },
    {
      "scope": "keyword.control.directive",
      "settings": {
        "foreground": "#FF657A"
      }
    },
    {
      "scope": [
        "keyword.operator",
        "keyword.operator.member",
        "keyword.operator.new"
      ],
      "settings": {
        "foreground": "#FF657A"
      }
    },
    {
      "scope": "keyword.other.substitution",
      "settings": {
        "foreground": "#888D94"
      }
    },
    {
      "scope": ["keyword.other.template.begin", "keyword.other.template.end"],
      "settings": {
        "foreground": "#FF657A"
      }
    },
    {
      "scope": [
        "keyword.operator.heading.restructuredtext",
        "keyword.operator.table.row.restructuredtext keyword.operator.table.data.restructuredtext"
      ],
      "settings": {
        "foreground": "#888D94"
      }
    },
    {
      "scope": "keyword.other.parenthesis.elm",
      "settings": {
        "foreground": "#888D94"
      }
    },
    {
      "scope": [
        "keyword.other.fn.rust",
        "keyword.other.rust",
        "keyword.other.unsafe.rust",
        "keyword.other.where.rust"
      ],
      "settings": {
        "foreground": "#9CD1BB"
      }
    },
    {
      "scope": ["keyword.control.rust", "keyword.operator.misc.rust"],
      "settings": {
        "foreground": "#FF657A"
      }
    },
    {
      "scope": [
        "keyword.declaration.class.ruby",
        "keyword.declaration.function.ruby",
        "keyword.declaration.namespace.ruby"
      ],
      "settings": {
        "foreground": "#FF657A"
      }
    },
    {
      "scope": "markup.italic",
      "settings": {
        "fontStyle": "italic"
      }
    },
    {
      "scope": "markup.bold",
      "settings": {
        "fontStyle": "bold"
      }
    },
    {
      "scope": "markup.heading",
      "settings": {
        "foreground": "#FFD76D"
      }
    },
    {
      "scope": "markup.raw",
      "settings": {
        "foreground": "#FF9B5E"
      }
    },
    {
      "scope": "markup.underline",
      "settings": {
        "fontStyle": "underline"
      }
    },
    {
      "scope": "markup.underline.link",
      "settings": {
        "foreground": "#BAD761"
      }
    },
    {
      "scope": [
        "markup.inserted",
        "markup.inserted punctuation.definition.inserted"
      ],
      "settings": {
        "foreground": "#BAD761"
      }
    },
    {
      "scope": [
        "markup.deleted",
        "markup.deleted punctuation.definition.deleted"
      ],
      "settings": {
        "foreground": "#FF657A"
      }
    },
    {
      "scope": [
        "markup.changed",
        "markup.changed punctuation.definition.changed"
      ],
      "settings": {
        "foreground": "#FFD76D"
      }
    },
    {
      "scope": [
        "markup.ignored",
        "markup.ignored punctuation.definition.ignored"
      ],
      "settings": {
        "foreground": "#888D94"
      }
    },
    {
      "scope": "markup.untracked",
      "settings": {
        "foreground": "#888D94"
      }
    },
    {
      "scope": "markup.quote",
      "settings": {
        "fontStyle": "italic"
      }
    },
    {
      "scope": [
        "meta.brace.round",
        "meta.brace.square",
        "meta.brace.curly",
        "meta.delimiter.comma.js",
        "meta.function-call.without-arguments.js",
        "meta.function-call.method.without-arguments.js"
      ],
      "settings": {
        "foreground": "#888D94"
      }
    },
    {
      "scope": [
        "meta.function-call.generic.python",
        "support.function.builtin.python"
      ],
      "settings": {
        "foreground": "#BAD761"
      }
    },
    {
      "scope": "meta.function-call.python meta.function-call.arguments.python",
      "settings": {
        "foreground": "#EAF2F1"
      }
    },
    {
      "scope": "meta.instance.constructor",
      "settings": {
        "foreground": "#BAD761"
      }
    },
    {
      "scope": [
        "meta.attribute-with-value.class string",
        "meta.attribute.class.html string"
      ],
      "settings": {
        "foreground": "#BAD761"
      }
    },
    {
      "scope": [
        "meta.attribute-with-value.id string",
        "meta.attribute.id.html string"
      ],
      "settings": {
        "foreground": "#FF9B5E"
      }
    },
    {
      "scope": "source.json meta.mapping.key string",
      "settings": {
        "foreground": "#EAF2F1"
      }
    },
    {
      "scope": "source.yaml meta.mapping.key string",
      "settings": {
        "foreground": "#FF657A"
      }
    },
    {
      "scope": "meta.object.member",
      "settings": {
        "foreground": "#EAF2F1"
      }
    },
    {
      "scope": "meta.property-list.css variable.other",
      "settings": {
        "foreground": "#695eff"
      }
    },
    {
      "scope": ["entity.name.constant.preprocessor", "meta.preprocessor"],
      "settings": {
        "foreground": "#C39AC9"
      }
    },
    {
      "scope": "meta.diff.git-diff.header",
      "settings": {
        "foreground": "#FFD76D"
      }
    },
    {
      "scope": "meta.type_params.rust",
      "settings": {
        "foreground": "#EAF2F1"
      }
    },
    {
      "scope": [
        "meta.attribute.rust",
        "meta.annotation.rust",
        "variable.language.rust",
        "variable.annotation.rust",
        "meta.annotation.rust string",
        "meta.annotation.rust keyword",
        "meta.annotation.rust keyword.operator",
        "meta.attribute.rust string"
      ],
      "settings": {
        "foreground": "#B2B9BD"
      }
    },
    {
      "scope": "punctuation",
      "settings": {
        "foreground": "#fafafa"
      }
    },
    {
      "scope": [
        "punctuation.definition.tag",
        "punctuation.definition.tag source",
        "punctuation.definition.group.begin.ruby",
        "punctuation.definition.group.end.ruby",
        "punctuation.definition.group.begin.css",
        "punctuation.definition.group.end.css",
        "punctuation.definition.string.end.html source.css"
      ],
      "settings": {
        "foreground": "#888D94"
      }
    },
    {
      "scope": "punctuation.definition.group",
      "settings": {
        "foreground": "#EAF2F1"
      }
    },
    {
      "scope": "punctuation.definition.comment",
      "settings": {
        "foreground": "#696D77"
      }
    },
    {
      "scope": [
        "punctuation.definition.variable",
        "punctuation.definition.keyword.scss",
        "punctuation.definition.entity.css"
      ],
      "settings": {
        "foreground": "#B2B9BD"
      }
    },
    {
      "scope": [
        "punctuation.section.embedded",
        "punctuation.section.embedded entity.name.tag",
        "punctuation.section.embedded constant.other",
        "punctuation.section.embedded source",
        "punctuation.section.embedded.begin"
      ],
      "settings": {
        "foreground": "#FF9B5E"
      }
    },
    {
      "scope": [
        "punctuation.template-string.element.begin",
        "punctuation.template-string.element.end",
        "punctuation.definition.string.template.begin",
        "punctuation.definition.string.template.end",
        "string.quoted.template punctuation.definition.string.begin",
        "string.quoted.template punctuation.definition.string.end",
        "punctuation.definition.template-expression.begin",
        "punctuation.definition.template-expression.end"
      ],
      "settings": {
        "foreground": "#FF657A"
      }
    },
    {
      "scope": [
        "meta.paragraph.markdown meta.dummy.line-break",
        "meta.paragraph.markdown meta.hard-line-break.markdown"
      ],
      "settings": {
        "background": "#C39AC9"
      }
    },
    {
      "scope": "markup.underline.link punctuation",
      "settings": {
        "foreground": "#BAD761"
      }
    },
    {
      "scope": "region.redish",
      "settings": {
        "foreground": "#FF657A",
        "background": "#FF657A59"
      }
    },
    {
      "scope": "region.orangish",
      "settings": {
        "foreground": "#FF9B5E",
        "background": "#FF9B5E59"
      }
    },
    {
      "scope": "region.yellowish",
      "settings": {
        "foreground": "#FFD76D",
        "background": "#FFD76D59"
      }
    },
    {
      "scope": "region.greenish",
      "settings": {
        "foreground": "#BAD761",
        "background": "#BAD76159"
      }
    },
    {
      "scope": "region.bluish",
      "settings": {
        "foreground": "#9CD1BB",
        "background": "#9CD1BB59"
      }
    },
    {
      "scope": "region.purplish",
      "settings": {
        "foreground": "#C39AC9",
        "background": "#C39AC959"
      }
    },
    {
      "scope": "region.pinkish",
      "settings": {
        "foreground": "#FF657A",
        "background": "#FF657A59"
      }
    },
    {
      "scope": "region.whitish",
      "settings": {
        "foreground": "#FFFFFF"
      }
    },
    {
      "scope": "source",
      "settings": {
        "foreground": "#EAF2F1"
      }
    },
    {
      "scope": ["source.scss", "source.sass"],
      "settings": {
        "foreground": "#888D94"
      }
    },
    {
      "scope": [
        "source.sass variable.other",
        "source.sass variable.sass",
        "source.scss variable.other",
        "source.scss variable.scss",
        "source.scss variable.sass",
        "source.css variable.other",
        "source.css variable.scss",
        "source.less variable.other",
        "source.less variable.other.less",
        "source.less variable.declaration.less"
      ],
      "settings": {
        "foreground": "#FF9B5E",
        "fontStyle": "italic"
      }
    },
    {
      "scope": "source.git-show.commit.sha",
      "settings": {
        "foreground": "#C39AC9"
      }
    },
    {
      "scope": [
        "source.git-show.author",
        "source.git-show.date",
        "source.git-diff.command",
        "source.git-diff.command meta.diff.git-diff.header.from-file",
        "source.git-diff.command meta.diff.git-diff.header.to-file"
      ],
      "settings": {
        "foreground": "#888D94"
      }
    },
    {
      "scope": [
        "source.git-show meta.diff.git-diff.header.extended.index.from-sha",
        "source.git-show meta.diff.git-diff.header.extended.index.to-sha"
      ],
      "settings": {
        "foreground": "#C39AC9"
      }
    },
    {
      "scope": "source.git-show meta.diff.range.unified",
      "settings": {
        "foreground": "#FF9B5E"
      }
    },
    {
      "scope": [
        "source.git-show meta.diff.header.from-file",
        "source.git-show meta.diff.header.to-file"
      ],
      "settings": {
        "foreground": "#888D94"
      }
    },
    {
      "scope": "storage",
      "settings": {
        "foreground": "#FF657A"
      }
    },
    {
      "scope": "storage.type",
      "settings": {
        "foreground": "#9CD1BB",
        "fontStyle": "italic"
      }
    },
    {
      "scope": "storage.type.extends",
      "settings": {
        "foreground": "#FF657A",
        "fontStyle": "normal"
      }
    },
    {
      "scope": "storage.type.function.arrow",
      "settings": {
        "foreground": "#FF657A",
        "fontStyle": "normal"
      }
    },
    {
      "scope": ["storage.modifier", "storage.type.modifier"],
      "settings": {
        "foreground": "#FF657A",
        "fontStyle": "italic"
      }
    },
    {
      "scope": "storage.class.restructuredtext.ref",
      "settings": {
        "foreground": "#C39AC9"
      }
    },
    {
      "scope": [
        "storage.modifier.visibility.rust",
        "storage.modifier.lifetime.rust"
      ],
      "settings": {
        "foreground": "#FF657A"
      }
    },
    {
      "scope": [
        "storage.modifier.const.rust",
        "storage.modifier.dyn.rust",
        "storage.modifier.mut.rust",
        "storage.modifier.static.rust",
        "storage.type.rust",
        "storage.type.core.rust",
        "storage.class.std.rust"
      ],
      "settings": {
        "foreground": "#9CD1BB"
      }
    },
    {
      "scope": [
        "storage.type.rust",
        "storage.modifier.const.rust",
        "storage.modifier.dyn.rust",
        "storage.modifier.mut.rust",
        "storage.modifier.static.rust",
        "keyword.other.rust",
        "keyword.other.where.rust"
      ],
      "settings": {
        "foreground": "#FF657A"
      }
    },
    {
      "scope": "string",
      "settings": {
        "foreground": "#FFD76D"
      }
    },
    {
      "scope": "string.unquoted.label",
      "settings": {
        "foreground": "#EAF2F1"
      }
    },
    {
      "scope": "string source",
      "settings": {
        "foreground": "#EAF2F1"
      }
    },
    {
      "scope": [
        "string source punctuation.section.embedded",
        "string punctuation.definition.string source"
      ],
      "settings": {
        "foreground": "#888D94"
      }
    },
    {
      "scope": ["string.other.link.title", "string.other.link.description"],
      "settings": {
        "foreground": "#FF657A"
      }
    },
    {
      "scope": "string.other.link.description.title",
      "settings": {
        "foreground": "#9CD1BB"
      }
    },
    {
      "scope": [
        "string.regexp punctuation.definition.string.begin",
        "string.regexp punctuation.definition.string.end"
      ],
      "settings": {
        "foreground": "#FF657A"
      }
    },
    {
      "scope": ["string.other.ref", "string.other.restructuredtext.ref"],
      "settings": {
        "foreground": "#BAD761"
      }
    },
    {
      "scope": "string.other.git-status.help.key",
      "settings": {
        "foreground": "#B2B9BD"
      }
    },
    {
      "scope": "string.other.git-status.remote",
      "settings": {
        "foreground": "#FF657A"
      }
    },
    {
      "scope": "support.constant",
      "settings": {
        "foreground": "#fff200"
      }
    },
    {
      "scope": "support.constant.handlebars",
      "settings": {
        "foreground": "#888D94"
      }
    },
    {
      "scope": "support.type.vendor-prefix.css",
      "settings": {
        "foreground": "#B2B9BD"
      }
    },
    {
      "scope": "support.function",
      "settings": {
        "foreground": "#ffff00"
      }
    },
    {
      "scope": "support.function.delimiter.elm",
      "settings": {
        "foreground": "#888D94"
      }
    },
    {
      "scope": ["support.type", "entity.name.type.object.console"],
      "settings": {
        "foreground": "#9CD1BB",
        "fontStyle": "italic"
      }
    },
    {
      "scope": "support.variable",
      "settings": {
        "foreground": "#9CD1BB"
      }
    },
    {
      "scope": "support.type.property-name",
      "settings": {
        "foreground": "#c5db97",
        "fontStyle": "normal"
      }
    },
    {
      "scope": "support.class",
      "settings": {
        "foreground": "#9CD1BB"
      }
    },
    {
      "scope": "support.constant.core.rust",
      "settings": {
        "foreground": "#C39AC9"
      }
    },
    {
      "scope": "text",
      "settings": {
        "foreground": "#EAF2F1"
      }
    },
    {
      "scope": "text.find-in-files",
      "settings": {
        "foreground": "#EAF2F1"
      }
    },
    {
      "scope": ["variable", "variable.other"],
      "settings": {
        "foreground": "#EAF2F1"
      }
    },
    {
      "scope": ["variable.parameter", "parameters variable.function"],
      "settings": {
        "foreground": "#FF9B5E",
        "fontStyle": "italic"
      }
    },
    {
      "scope": [
        "variable.language",
        "variable.parameter.function.language.special.self.python",
        "variable.parameter.function.language.special.cls.python"
      ],
      "settings": {
        "foreground": "#B2B9BD",
        "fontStyle": "italic"
      }
    },
    {
      "scope": "variable.language.arguments",
      "settings": {
        "foreground": "#C39AC9"
      }
    },
    {
      "scope": "variable.other.class",
      "settings": {
        "foreground": "#9CD1BB"
      }
    },
    {
      "scope": "variable.other.constant",
      "settings": {
        "foreground": "#29ff6d"
      }
    },
    {
      "scope": "variable.other.readwrite",
      "settings": {
        "foreground": "#EAF2F1"
      }
    },
    {
      "scope": "variable.other.member",
      "settings": {
        "foreground": "#EAF2F1"
      }
    },
    {
      "scope": "variable.other.enummember",
      "settings": {
        "foreground": "#C39AC9"
      }
    },
    {
      "scope": [
        "variable.other.property",
        "variable.other.property.static",
        "variable.other.event"
      ],
      "settings": {
        "foreground": "#EAF2F1"
      }
    },
    {
      "scope": "variable.function",
      "settings": {
        "foreground": "#BAD761"
      }
    },
    {
      "scope": "variable.other.substitution",
      "settings": {
        "foreground": "#FF9B5E"
      }
    },
    {
      "scope": [
        "source.ruby variable.other.readwrite.instance.ruby",
        "source.ruby variable.other.readwrite.class.ruby"
      ],
      "settings": {
        "foreground": "#C39AC9"
      }
    },
    {
      "scope": "source.jinja2 variable.other.jinja2.block",
      "settings": {
        "foreground": "#BAD761"
      }
    },
    {
      "scope": "source.jinja2 variable.other.jinja2",
      "settings": {
        "foreground": "#FF9B5E"
      }
    },
    {
      "scope": "comment",
      "settings": {
        "foreground": "#9A9A9A"
      }
    },
    {
      "scope": "punctuation.definition.comment",
      "settings": {
        "foreground": "#9A9A9A"
      }
    },
    {
      "scope": "token.info-token",
      "settings": {
        "foreground": "#6796E6"
      }
    },
    {
      "scope": "token.warn-token",
      "settings": {
        "foreground": "#CD9731"
      }
    },
    {
      "scope": "token.error-token",
      "settings": {
        "foreground": "#F44747"
      }
    },
    {
      "scope": "token.debug-token",
      "settings": {
        "foreground": "#B267E6"
      }
    }
  ]
}
